insta_fetcher/__init__.py
insta_fetcher/ins_fetcher.py
insta_fetcher-0.1.1.dist-info/METADATA
insta_fetcher-0.1.1.dist-info/WHEEL
insta_fetcher-0.1.1.dist-info/entry_points.txt
insta_fetcher-0.1.1.dist-info/top_level.txt
insta_fetcher-0.1.1.dist-info/RECORD
