Metadata-Version: 2.1
Name: insta_fetcher
Version: 0.1.1
Summary: A script to fetch and organize Instagram data using instaloader
Home-page: https://github.com/IvesLiu1026/insta-fetcher
Author: Ives Liu
Author-email: ivesliutaiwan@gmail.com
Classifier: Programming Language :: Python :: 3
Classifier: License :: OSI Approved :: MIT License
Classifier: Operating System :: OS Independent
Requires-Python: >=3.6
Requires-Dist: instaloader
